okta_custom_cli/__init__.py
okta_custom_cli/okta.py
okta_custom_cli/utils.py
okta_custom_cli-0.0.4.dist-info/LICENCE.txt
okta_custom_cli-0.0.4.dist-info/METADATA
okta_custom_cli-0.0.4.dist-info/WHEEL
okta_custom_cli-0.0.4.dist-info/entry_points.txt
okta_custom_cli-0.0.4.dist-info/top_level.txt
okta_custom_cli-0.0.4.dist-info/zip-safe
okta_custom_cli-0.0.4.dist-info/RECORD
