Metadata-Version: 2.1
Name: okta-custom-cli
Version: 0.0.4
Summary: Sample Okta CLI tool in python
Home-page: UNKNOWN
Author: Atulya Kumar Pandey
Author-email: atul3015@gmail.com
License: MIT
Platform: UNKNOWN
Requires-Dist: Click
Requires-Dist: pyfiglet
Requires-Dist: requests
